open_bobj/__init__.py
open_bobj/main.py
open_bobj/obj_import.py
open_bobj-0.1.1.dist-info/LICENSE
open_bobj-0.1.1.dist-info/METADATA
open_bobj-0.1.1.dist-info/WHEEL
open_bobj-0.1.1.dist-info/entry_points.txt
open_bobj-0.1.1.dist-info/top_level.txt
open_bobj-0.1.1.dist-info/RECORD
