Metadata-Version: 2.1
Name: open-bobj
Version: 0.1.1
Summary: Open obj files in Blender from Terminal
Home-page: https://github.com/PraxTube/open-bobj
Author: Prax
Project-URL: Bug Reports, https://github.com/PraxTube/open-bobj/issues
Project-URL: Source, https://github.com/PraxTube/open-bobj
Keywords: blender,obj
Classifier: Development Status :: 3 - Alpha
Classifier: License :: OSI Approved :: MIT License
Classifier: Programming Language :: Python :: 3
Classifier: Programming Language :: Python :: 3.8
Classifier: Programming Language :: Python :: 3.9
Classifier: Programming Language :: Python :: 3.10
Classifier: Programming Language :: Python :: 3 :: Only
Requires-Python: >=3.8, <4
License-File: LICENSE
